previsedx_labguru_file_utils/__init__.py
previsedx_labguru_file_utils/console_helper.py
previsedx_labguru_file_utils/constants.py
previsedx_labguru_file_utils/file_utils.py
previsedx_labguru_file_utils/parser.py
previsedx_labguru_file_utils/record.py
previsedx_labguru_file_utils/system_caller.py
previsedx_labguru_file_utils/conf/config.yaml
previsedx_labguru_file_utils/xlsx/__init__.py
previsedx_labguru_file_utils/xlsx/parser.py
previsedx_labguru_file_utils-0.1.0.dist-info/AUTHORS.rst
previsedx_labguru_file_utils-0.1.0.dist-info/LICENSE
previsedx_labguru_file_utils-0.1.0.dist-info/METADATA
previsedx_labguru_file_utils-0.1.0.dist-info/WHEEL
previsedx_labguru_file_utils-0.1.0.dist-info/top_level.txt
previsedx_labguru_file_utils-0.1.0.dist-info/RECORD
